moneymatters/__init__.py
moneymatters/api.py
moneymatters-2024.5.3.dist-info/LICENSE
moneymatters-2024.5.3.dist-info/METADATA
moneymatters-2024.5.3.dist-info/WHEEL
moneymatters-2024.5.3.dist-info/top_level.txt
moneymatters-2024.5.3.dist-info/RECORD
