Metadata-Version: 2.1
Name: moneymatters
Version: 2024.5.3
Summary: A Python package that encompasses money related stuff into one package - money formatting, currency conversion etc
Home-page: https://github.com/musicmuni/moneymatters
Author: Gopala Krishna Koduri
Author-email: gopal@riyazapp.com
Project-URL: Source Code, https://github.com/musicmuni/moneymatters
Project-URL: Issue Tracker, https://github.com/musicmuni/moneymatters/issues
Project-URL: Connect w/ Author, https://linkedin.com/in/gopalkoduri
Project-URL: Riyaz - Learn to sing, https://riyazapp.com
Classifier: Development Status :: 3 - Alpha
Classifier: Intended Audience :: Developers
Classifier: Topic :: Software Development :: Build Tools
Classifier: License :: OSI Approved :: MIT License
Classifier: Programming Language :: Python :: 3
Classifier: Programming Language :: Python :: 3.7
Classifier: Programming Language :: Python :: 3.8
Classifier: Programming Language :: Python :: 3.9
Classifier: Programming Language :: Python :: 3.10
Classifier: Programming Language :: Python :: 3.11
License-File: LICENSE
Requires-Dist: CurrencyConverter
Requires-Dist: requests
Requires-Dist: beautifulsoup4
